setup.py
doodads/__init__.py
doodads.egg-info/PKG-INFO
doodads.egg-info/SOURCES.txt
doodads.egg-info/dependency_links.txt
doodads.egg-info/top_level.txt