Metadata-Version: 1.1
Name: doodads
Version: 0.0.0
Summary: A hodgepodge of wild and exciting doodads
Home-page: https://github.com/bp256r1/doodads
Author: Tyler Fisher
Author-email: podgeracer9000@gmail.com
License: MIT
Platform: UNKNOWN
Classifier: License :: OSI Approved :: MIT License
Classifier: Programming Language :: Python
Classifier: Environment :: Console
Classifier: Intended Audience :: Developers
